<class>
  <keyword> class </keyword>
  <identifier kind="NONE" type="Main" index="0"> Main </identifier>
  <symbol> { </symbol>
  <subroutineDec VarCount=3>
    <keyword> function </keyword>
    <keyword> void </keyword>
    <identifier kind="NONE" type="void" index="0"> main </identifier>
    <symbol> ( </symbol>
    <parameterList>
    </parameterList>
    <symbol> ) </symbol>
    <subroutineBody>
      <symbol> { </symbol>
      <varDec>
        <keyword> var </keyword>
        <identifier kind="NONE" type="" index="0"> Array </identifier>
        <identifier kind="VAR" type="Array" index="0"> a </identifier>
        <symbol> , </symbol>
        <identifier kind="VAR" type="Array" index="1"> b </identifier>
        <symbol> , </symbol>
        <identifier kind="VAR" type="Array" index="2"> c </identifier>
        <symbol> ; </symbol>
      </varDec>
      <statements>
        <letStatement>
          <keyword> let </keyword>
          <identifier kind="VAR" type="Array" index="0"> a </identifier>
          <symbol> = </symbol>
          <expression>
            <term>
              <identifier kind="NONE" type="" index="0"> Array </identifier>
              <symbol> . </symbol>
              <identifier kind="NONE" type="" index="0"> new </identifier>
              <symbol> ( </symbol>
              <expressionList>
                <expression>
                  <term>
                    <integerConstant> 10 </integerConstant>
                  </term>
                </expression>
              </expressionList>
              <symbol> ) </symbol>
            </term>
          </expression>
          <symbol> ; </symbol>
        </letStatement>
        <letStatement>
          <keyword> let </keyword>
          <identifier kind="VAR" type="Array" index="1"> b </identifier>
          <symbol> = </symbol>
          <expression>
            <term>
              <identifier kind="NONE" type="" index="0"> Array </identifier>
              <symbol> . </symbol>
              <identifier kind="NONE" type="" index="0"> new </identifier>
              <symbol> ( </symbol>
              <expressionList>
                <expression>
                  <term>
                    <integerConstant> 5 </integerConstant>
                  </term>
                </expression>
              </expressionList>
              <symbol> ) </symbol>
            </term>
          </expression>
          <symbol> ; </symbol>
        </letStatement>
        <letStatement>
          <keyword> let </keyword>
          <identifier kind="VAR" type="Array" index="2"> c </identifier>
          <symbol> = </symbol>
          <expression>
            <term>
              <identifier kind="NONE" type="" index="0"> Array </identifier>
              <symbol> . </symbol>
              <identifier kind="NONE" type="" index="0"> new </identifier>
              <symbol> ( </symbol>
              <expressionList>
                <expression>
                  <term>
                    <integerConstant> 1 </integerConstant>
                  </term>
                </expression>
              </expressionList>
              <symbol> ) </symbol>
            </term>
          </expression>
          <symbol> ; </symbol>
        </letStatement>
        <letStatement>
          <keyword> let </keyword>
          <identifier kind="VAR" type="Array" index="0"> a </identifier>
          <symbol> [ </symbol>
          <expression>
            <term>
              <integerConstant> 3 </integerConstant>
            </term>
          </expression>
          <symbol> ] </symbol>
          <symbol> = </symbol>
          <expression>
            <term>
              <integerConstant> 2 </integerConstant>
            </term>
          </expression>
          <symbol> ; </symbol>
        </letStatement>
        <letStatement>
          <keyword> let </keyword>
          <identifier kind="VAR" type="Array" index="0"> a </identifier>
          <symbol> [ </symbol>
          <expression>
            <term>
              <integerConstant> 4 </integerConstant>
            </term>
          </expression>
          <symbol> ] </symbol>
          <symbol> = </symbol>
          <expression>
            <term>
              <integerConstant> 8 </integerConstant>
            </term>
          </expression>
          <symbol> ; </symbol>
        </letStatement>
        <letStatement>
          <keyword> let </keyword>
          <identifier kind="VAR" type="Array" index="0"> a </identifier>
          <symbol> [ </symbol>
          <expression>
            <term>
              <integerConstant> 5 </integerConstant>
            </term>
          </expression>
          <symbol> ] </symbol>
          <symbol> = </symbol>
          <expression>
            <term>
              <integerConstant> 4 </integerConstant>
            </term>
          </expression>
          <symbol> ; </symbol>
        </letStatement>
        <letStatement>
          <keyword> let </keyword>
          <identifier kind="VAR" type="Array" index="1"> b </identifier>
          <symbol> [ </symbol>
          <expression>
            <term>
              <identifier kind="VAR" type="Array" index="0"> a </identifier>
              <symbol> [ </symbol>
              <expression>
                <term>
                  <integerConstant> 3 </integerConstant>
                </term>
              </expression>
              <symbol> ] </symbol>
            </term>
          </expression>
          <symbol> ] </symbol>
          <symbol> = </symbol>
          <expression>
            <term>
              <identifier kind="VAR" type="Array" index="0"> a </identifier>
              <symbol> [ </symbol>
              <expression>
                <term>
                  <integerConstant> 3 </integerConstant>
                </term>
              </expression>
              <symbol> ] </symbol>
            </term>
            <symbol> + </symbol>
            <term>
              <integerConstant> 3 </integerConstant>
            </term>
          </expression>
          <symbol> ; </symbol>
        </letStatement>
        <letStatement>
          <keyword> let </keyword>
          <identifier kind="VAR" type="Array" index="0"> a </identifier>
          <symbol> [ </symbol>
          <expression>
            <term>
              <identifier kind="VAR" type="Array" index="1"> b </identifier>
              <symbol> [ </symbol>
              <expression>
                <term>
                  <identifier kind="VAR" type="Array" index="0"> a </identifier>
                  <symbol> [ </symbol>
                  <expression>
                    <term>
                      <integerConstant> 3 </integerConstant>
                    </term>
                  </expression>
                  <symbol> ] </symbol>
                </term>
              </expression>
              <symbol> ] </symbol>
            </term>
          </expression>
          <symbol> ] </symbol>
          <symbol> = </symbol>
          <expression>
            <term>
              <identifier kind="VAR" type="Array" index="0"> a </identifier>
              <symbol> [ </symbol>
              <expression>
                <term>
                  <identifier kind="VAR" type="Array" index="0"> a </identifier>
                  <symbol> [ </symbol>
                  <expression>
                    <term>
                      <integerConstant> 5 </integerConstant>
                    </term>
                  </expression>
                  <symbol> ] </symbol>
                </term>
              </expression>
              <symbol> ] </symbol>
            </term>
            <symbol> * </symbol>
            <term>
              <identifier kind="VAR" type="Array" index="1"> b </identifier>
              <symbol> [ </symbol>
              <expression>
                <term>
                  <integerConstant> 7 </integerConstant>
                </term>
                <symbol> - </symbol>
                <term>
                  <identifier kind="VAR" type="Array" index="0"> a </identifier>
                  <symbol> [ </symbol>
                  <expression>
                    <term>
                      <integerConstant> 3 </integerConstant>
                    </term>
                  </expression>
                  <symbol> ] </symbol>
                </term>
                <symbol> - </symbol>
                <term>
                  <identifier kind="NONE" type="" index="0"> Main </identifier>
                  <symbol> . </symbol>
                  <identifier kind="NONE" type="" index="0"> double </identifier>
                  <symbol> ( </symbol>
                  <expressionList>
                    <expression>
                      <term>
                        <integerConstant> 2 </integerConstant>
                      </term>
                    </expression>
                  </expressionList>
                  <symbol> ) </symbol>
                </term>
                <symbol> + </symbol>
                <term>
                  <integerConstant> 1 </integerConstant>
                </term>
              </expression>
              <symbol> ] </symbol>
            </term>
          </expression>
          <symbol> ; </symbol>
        </letStatement>
        <letStatement>
          <keyword> let </keyword>
          <identifier kind="VAR" type="Array" index="2"> c </identifier>
          <symbol> [ </symbol>
          <expression>
            <term>
              <integerConstant> 0 </integerConstant>
            </term>
          </expression>
          <symbol> ] </symbol>
          <symbol> = </symbol>
          <expression>
            <term>
              <keyword> null </keyword>
            </term>
          </expression>
          <symbol> ; </symbol>
        </letStatement>
        <letStatement>
          <keyword> let </keyword>
          <identifier kind="VAR" type="Array" index="2"> c </identifier>
          <symbol> = </symbol>
          <expression>
            <term>
              <identifier kind="VAR" type="Array" index="2"> c </identifier>
              <symbol> [ </symbol>
              <expression>
                <term>
                  <integerConstant> 0 </integerConstant>
                </term>
              </expression>
              <symbol> ] </symbol>
            </term>
          </expression>
          <symbol> ; </symbol>
        </letStatement>
        <doStatement>
          <keyword> do </keyword>
          <identifier kind="NONE" type="" index="0"> Output </identifier>
          <symbol> . </symbol>
          <identifier kind="NONE" type="" index="0"> printString </identifier>
          <symbol> ( </symbol>
          <expressionList>
            <expression>
              <term>
                <stringConstant> Test 1 - Required result: 5, Actual result:  </stringConstant>
              </term>
            </expression>
          </expressionList>
          <symbol> ) </symbol>
          <symbol> ; </symbol>
        </doStatement>
        <doStatement>
          <keyword> do </keyword>
          <identifier kind="NONE" type="" index="0"> Output </identifier>
          <symbol> . </symbol>
          <identifier kind="NONE" type="" index="0"> printInt </identifier>
          <symbol> ( </symbol>
          <expressionList>
            <expression>
              <term>
                <identifier kind="VAR" type="Array" index="1"> b </identifier>
                <symbol> [ </symbol>
                <expression>
                  <term>
                    <integerConstant> 2 </integerConstant>
                  </term>
                </expression>
                <symbol> ] </symbol>
              </term>
            </expression>
          </expressionList>
          <symbol> ) </symbol>
          <symbol> ; </symbol>
        </doStatement>
        <doStatement>
          <keyword> do </keyword>
          <identifier kind="NONE" type="" index="0"> Output </identifier>
          <symbol> . </symbol>
          <identifier kind="NONE" type="" index="0"> println </identifier>
          <symbol> ( </symbol>
          <expressionList>
          </expressionList>
          <symbol> ) </symbol>
          <symbol> ; </symbol>
        </doStatement>
        <doStatement>
          <keyword> do </keyword>
          <identifier kind="NONE" type="" index="0"> Output </identifier>
          <symbol> . </symbol>
          <identifier kind="NONE" type="" index="0"> printString </identifier>
          <symbol> ( </symbol>
          <expressionList>
            <expression>
              <term>
                <stringConstant> Test 2 - Required result: 40, Actual result:  </stringConstant>
              </term>
            </expression>
          </expressionList>
          <symbol> ) </symbol>
          <symbol> ; </symbol>
        </doStatement>
        <doStatement>
          <keyword> do </keyword>
          <identifier kind="NONE" type="" index="0"> Output </identifier>
          <symbol> . </symbol>
          <identifier kind="NONE" type="" index="0"> printInt </identifier>
          <symbol> ( </symbol>
          <expressionList>
            <expression>
              <term>
                <identifier kind="VAR" type="Array" index="0"> a </identifier>
                <symbol> [ </symbol>
                <expression>
                  <term>
                    <integerConstant> 5 </integerConstant>
                  </term>
                </expression>
                <symbol> ] </symbol>
              </term>
            </expression>
          </expressionList>
          <symbol> ) </symbol>
          <symbol> ; </symbol>
        </doStatement>
        <doStatement>
          <keyword> do </keyword>
          <identifier kind="NONE" type="" index="0"> Output </identifier>
          <symbol> . </symbol>
          <identifier kind="NONE" type="" index="0"> println </identifier>
          <symbol> ( </symbol>
          <expressionList>
          </expressionList>
          <symbol> ) </symbol>
          <symbol> ; </symbol>
        </doStatement>
        <doStatement>
          <keyword> do </keyword>
          <identifier kind="NONE" type="" index="0"> Output </identifier>
          <symbol> . </symbol>
          <identifier kind="NONE" type="" index="0"> printString </identifier>
          <symbol> ( </symbol>
          <expressionList>
            <expression>
              <term>
                <stringConstant> Test 3 - Required result: 0, Actual result:  </stringConstant>
              </term>
            </expression>
          </expressionList>
          <symbol> ) </symbol>
          <symbol> ; </symbol>
        </doStatement>
        <doStatement>
          <keyword> do </keyword>
          <identifier kind="NONE" type="" index="0"> Output </identifier>
          <symbol> . </symbol>
          <identifier kind="NONE" type="" index="0"> printInt </identifier>
          <symbol> ( </symbol>
          <expressionList>
            <expression>
              <term>
                <identifier kind="VAR" type="Array" index="2"> c </identifier>
              </term>
            </expression>
          </expressionList>
          <symbol> ) </symbol>
          <symbol> ; </symbol>
        </doStatement>
        <doStatement>
          <keyword> do </keyword>
          <identifier kind="NONE" type="" index="0"> Output </identifier>
          <symbol> . </symbol>
          <identifier kind="NONE" type="" index="0"> println </identifier>
          <symbol> ( </symbol>
          <expressionList>
          </expressionList>
          <symbol> ) </symbol>
          <symbol> ; </symbol>
        </doStatement>
        <letStatement>
          <keyword> let </keyword>
          <identifier kind="VAR" type="Array" index="2"> c </identifier>
          <symbol> = </symbol>
          <expression>
            <term>
              <keyword> null </keyword>
            </term>
          </expression>
          <symbol> ; </symbol>
        </letStatement>
        <ifStatement>
          <keyword> if </keyword>
          <symbol> ( </symbol>
          <expression>
            <term>
              <identifier kind="VAR" type="Array" index="2"> c </identifier>
            </term>
            <symbol> = </symbol>
            <term>
              <keyword> null </keyword>
            </term>
          </expression>
          <symbol> ) </symbol>
          <symbol> { </symbol>
          <statements>
            <doStatement>
              <keyword> do </keyword>
              <identifier kind="NONE" type="" index="0"> Main </identifier>
              <symbol> . </symbol>
              <identifier kind="NONE" type="" index="0"> fill </identifier>
              <symbol> ( </symbol>
              <expressionList>
                <expression>
                  <term>
                    <identifier kind="VAR" type="Array" index="0"> a </identifier>
                  </term>
                </expression>
                <symbol> , </symbol>
                <expression>
                  <term>
                    <integerConstant> 10 </integerConstant>
                  </term>
                </expression>
              </expressionList>
              <symbol> ) </symbol>
              <symbol> ; </symbol>
            </doStatement>
            <letStatement>
              <keyword> let </keyword>
              <identifier kind="VAR" type="Array" index="2"> c </identifier>
              <symbol> = </symbol>
              <expression>
                <term>
                  <identifier kind="VAR" type="Array" index="0"> a </identifier>
                  <symbol> [ </symbol>
                  <expression>
                    <term>
                      <integerConstant> 3 </integerConstant>
                    </term>
                  </expression>
                  <symbol> ] </symbol>
                </term>
              </expression>
              <symbol> ; </symbol>
            </letStatement>
            <letStatement>
              <keyword> let </keyword>
              <identifier kind="VAR" type="Array" index="2"> c </identifier>
              <symbol> [ </symbol>
              <expression>
                <term>
                  <integerConstant> 1 </integerConstant>
                </term>
              </expression>
              <symbol> ] </symbol>
              <symbol> = </symbol>
              <expression>
                <term>
                  <integerConstant> 33 </integerConstant>
                </term>
              </expression>
              <symbol> ; </symbol>
            </letStatement>
            <letStatement>
              <keyword> let </keyword>
              <identifier kind="VAR" type="Array" index="2"> c </identifier>
              <symbol> = </symbol>
              <expression>
                <term>
                  <identifier kind="VAR" type="Array" index="0"> a </identifier>
                  <symbol> [ </symbol>
                  <expression>
                    <term>
                      <integerConstant> 7 </integerConstant>
                    </term>
                  </expression>
                  <symbol> ] </symbol>
                </term>
              </expression>
              <symbol> ; </symbol>
            </letStatement>
            <letStatement>
              <keyword> let </keyword>
              <identifier kind="VAR" type="Array" index="2"> c </identifier>
              <symbol> [ </symbol>
              <expression>
                <term>
                  <integerConstant> 1 </integerConstant>
                </term>
              </expression>
              <symbol> ] </symbol>
              <symbol> = </symbol>
              <expression>
                <term>
                  <integerConstant> 77 </integerConstant>
                </term>
              </expression>
              <symbol> ; </symbol>
            </letStatement>
            <letStatement>
              <keyword> let </keyword>
              <identifier kind="VAR" type="Array" index="1"> b </identifier>
              <symbol> = </symbol>
              <expression>
                <term>
                  <identifier kind="VAR" type="Array" index="0"> a </identifier>
                  <symbol> [ </symbol>
                  <expression>
                    <term>
                      <integerConstant> 3 </integerConstant>
                    </term>
                  </expression>
                  <symbol> ] </symbol>
                </term>
              </expression>
              <symbol> ; </symbol>
            </letStatement>
            <letStatement>
              <keyword> let </keyword>
              <identifier kind="VAR" type="Array" index="1"> b </identifier>
              <symbol> [ </symbol>
              <expression>
                <term>
                  <integerConstant> 1 </integerConstant>
                </term>
              </expression>
              <symbol> ] </symbol>
              <symbol> = </symbol>
              <expression>
                <term>
                  <identifier kind="VAR" type="Array" index="1"> b </identifier>
                  <symbol> [ </symbol>
                  <expression>
                    <term>
                      <integerConstant> 1 </integerConstant>
                    </term>
                  </expression>
                  <symbol> ] </symbol>
                </term>
                <symbol> + </symbol>
                <term>
                  <identifier kind="VAR" type="Array" index="2"> c </identifier>
                  <symbol> [ </symbol>
                  <expression>
                    <term>
                      <integerConstant> 1 </integerConstant>
                    </term>
                  </expression>
                  <symbol> ] </symbol>
                </term>
              </expression>
              <symbol> ; </symbol>
            </letStatement>
          </statements>
          <symbol> } </symbol>
        </ifStatement>
        <doStatement>
          <keyword> do </keyword>
          <identifier kind="NONE" type="" index="0"> Output </identifier>
          <symbol> . </symbol>
          <identifier kind="NONE" type="" index="0"> printString </identifier>
          <symbol> ( </symbol>
          <expressionList>
            <expression>
              <term>
                <stringConstant> Test 4 - Required result: 77, Actual result:  </stringConstant>
              </term>
            </expression>
          </expressionList>
          <symbol> ) </symbol>
          <symbol> ; </symbol>
        </doStatement>
        <doStatement>
          <keyword> do </keyword>
          <identifier kind="NONE" type="" index="0"> Output </identifier>
          <symbol> . </symbol>
          <identifier kind="NONE" type="" index="0"> printInt </identifier>
          <symbol> ( </symbol>
          <expressionList>
            <expression>
              <term>
                <identifier kind="VAR" type="Array" index="2"> c </identifier>
                <symbol> [ </symbol>
                <expression>
                  <term>
                    <integerConstant> 1 </integerConstant>
                  </term>
                </expression>
                <symbol> ] </symbol>
              </term>
            </expression>
          </expressionList>
          <symbol> ) </symbol>
          <symbol> ; </symbol>
        </doStatement>
        <doStatement>
          <keyword> do </keyword>
          <identifier kind="NONE" type="" index="0"> Output </identifier>
          <symbol> . </symbol>
          <identifier kind="NONE" type="" index="0"> println </identifier>
          <symbol> ( </symbol>
          <expressionList>
          </expressionList>
          <symbol> ) </symbol>
          <symbol> ; </symbol>
        </doStatement>
        <doStatement>
          <keyword> do </keyword>
          <identifier kind="NONE" type="" index="0"> Output </identifier>
          <symbol> . </symbol>
          <identifier kind="NONE" type="" index="0"> printString </identifier>
          <symbol> ( </symbol>
          <expressionList>
            <expression>
              <term>
                <stringConstant> Test 5 - Required result: 110, Actual result:  </stringConstant>
              </term>
            </expression>
          </expressionList>
          <symbol> ) </symbol>
          <symbol> ; </symbol>
        </doStatement>
        <doStatement>
          <keyword> do </keyword>
          <identifier kind="NONE" type="" index="0"> Output </identifier>
          <symbol> . </symbol>
          <identifier kind="NONE" type="" index="0"> printInt </identifier>
          <symbol> ( </symbol>
          <expressionList>
            <expression>
              <term>
                <identifier kind="VAR" type="Array" index="1"> b </identifier>
                <symbol> [ </symbol>
                <expression>
                  <term>
                    <integerConstant> 1 </integerConstant>
                  </term>
                </expression>
                <symbol> ] </symbol>
              </term>
            </expression>
          </expressionList>
          <symbol> ) </symbol>
          <symbol> ; </symbol>
        </doStatement>
        <doStatement>
          <keyword> do </keyword>
          <identifier kind="NONE" type="" index="0"> Output </identifier>
          <symbol> . </symbol>
          <identifier kind="NONE" type="" index="0"> println </identifier>
          <symbol> ( </symbol>
          <expressionList>
          </expressionList>
          <symbol> ) </symbol>
          <symbol> ; </symbol>
        </doStatement>
        <returnStatement>
          <keyword> return </keyword>
          <symbol> ; </symbol>
        </returnStatement>
      </statements>
      <symbol> } </symbol>
    </subroutineBody>
  </subroutineDec>
  <subroutineDec VarCount=0>
    <keyword> function </keyword>
    <keyword> int </keyword>
    <identifier kind="NONE" type="int" index="0"> double </identifier>
    <symbol> ( </symbol>
    <parameterList>
      <keyword> int </keyword>
      <identifier kind="ARG" type="int" index="0"> a </identifier>
    </parameterList>
    <symbol> ) </symbol>
    <subroutineBody>
      <symbol> { </symbol>
      <statements>
        <returnStatement>
          <keyword> return </keyword>
          <expression>
            <term>
              <identifier kind="ARG" type="int" index="0"> a </identifier>
            </term>
            <symbol> * </symbol>
            <term>
              <integerConstant> 2 </integerConstant>
            </term>
          </expression>
          <symbol> ; </symbol>
        </returnStatement>
      </statements>
      <symbol> } </symbol>
    </subroutineBody>
  </subroutineDec>
  <subroutineDec VarCount=0>
    <keyword> function </keyword>
    <keyword> void </keyword>
    <identifier kind="NONE" type="void" index="0"> fill </identifier>
    <symbol> ( </symbol>
    <parameterList>
      <identifier kind="NONE" type="" index="0"> Array </identifier>
      <identifier kind="ARG" type="Array" index="0"> a </identifier>
      <symbol> , </symbol>
      <keyword> int </keyword>
      <identifier kind="ARG" type="int" index="1"> size </identifier>
    </parameterList>
    <symbol> ) </symbol>
    <subroutineBody>
      <symbol> { </symbol>
      <statements>
        <whileStatement>
          <keyword> while </keyword>
          <symbol> ( </symbol>
          <expression>
            <term>
              <identifier kind="ARG" type="int" index="1"> size </identifier>
            </term>
            <symbol> &gt; </symbol>
            <term>
              <integerConstant> 0 </integerConstant>
            </term>
          </expression>
          <symbol> ) </symbol>
          <symbol> { </symbol>
          <statements>
            <letStatement>
              <keyword> let </keyword>
              <identifier kind="ARG" type="int" index="1"> size </identifier>
              <symbol> = </symbol>
              <expression>
                <term>
                  <identifier kind="ARG" type="int" index="1"> size </identifier>
                </term>
                <symbol> - </symbol>
                <term>
                  <integerConstant> 1 </integerConstant>
                </term>
              </expression>
              <symbol> ; </symbol>
            </letStatement>
            <letStatement>
              <keyword> let </keyword>
              <identifier kind="ARG" type="Array" index="0"> a </identifier>
              <symbol> [ </symbol>
              <expression>
                <term>
                  <identifier kind="ARG" type="int" index="1"> size </identifier>
                </term>
              </expression>
              <symbol> ] </symbol>
              <symbol> = </symbol>
              <expression>
                <term>
                  <identifier kind="NONE" type="" index="0"> Array </identifier>
                  <symbol> . </symbol>
                  <identifier kind="NONE" type="" index="0"> new </identifier>
                  <symbol> ( </symbol>
                  <expressionList>
                    <expression>
                      <term>
                        <integerConstant> 3 </integerConstant>
                      </term>
                    </expression>
                  </expressionList>
                  <symbol> ) </symbol>
                </term>
              </expression>
              <symbol> ; </symbol>
            </letStatement>
          </statements>
          <symbol> } </symbol>
        </whileStatement>
        <returnStatement>
          <keyword> return </keyword>
          <symbol> ; </symbol>
        </returnStatement>
      </statements>
      <symbol> } </symbol>
    </subroutineBody>
  </subroutineDec>
  <symbol> } </symbol>
</class>
